aether_cli/__init__.py
aether_cli/__main__.py
aether_cli/build_process.py
aether_cli/cli.py
aether_cli/configs.py
aether_cli/run_server.py
aether_cli/utils.py
pyaether_cli-0.0.4.dist-info/METADATA
pyaether_cli-0.0.4.dist-info/WHEEL
pyaether_cli-0.0.4.dist-info/entry_points.txt
pyaether_cli-0.0.4.dist-info/RECORD
