Metadata-Version: 2.4
Name: pyaether-cli
Version: 0.0.4
Summary: A CLI to build and run dev server for Aether apps.
Project-URL: homepage, https://github.com/pyaether/aether-cli
Project-URL: repository, https://github.com/pyaether/aether-cli
Project-URL: documentation, https://github.com/pyaether/aether-cli
Author-email: Saurabh Ghanekar <ghanekarsaurabh8@gmail.com>
License-Expression: BSD-2-Clause
Classifier: Operating System :: OS Independent
Classifier: Programming Language :: Python :: 3
Requires-Python: >=3.10
Requires-Dist: beautifulsoup4>=4.13
Requires-Dist: click>=8.1
Requires-Dist: pyaether
Requires-Dist: pydantic>=2.10
Requires-Dist: rich>=13.9
Requires-Dist: typing-extensions>=4
